.semver
LICENSE.rst
MANIFEST.in
README.rst
requirements.txt
setup.py
nyawc/Crawler.py
nyawc/CrawlerActions.py
nyawc/CrawlerThread.py
nyawc/Options.py
nyawc/Queue.py
nyawc/QueueItem.py
nyawc/Routing.py
nyawc/__init__.py
nyawc.egg-info/PKG-INFO
nyawc.egg-info/SOURCES.txt
nyawc.egg-info/dependency_links.txt
nyawc.egg-info/requires.txt
nyawc.egg-info/top_level.txt
nyawc/helpers/DebugHelper.py
nyawc/helpers/HTTPRequestHelper.py
nyawc/helpers/PackageHelper.py
nyawc/helpers/RandomInputHelper.py
nyawc/helpers/URLHelper.py
nyawc/helpers/__init__.py
nyawc/http/Handler.py
nyawc/http/Request.py
nyawc/http/Response.py
nyawc/http/__init__.py
nyawc/scrapers/BaseScraper.py
nyawc/scrapers/CSSRegexLinkScraper.py
nyawc/scrapers/HTMLSoupFormScraper.py
nyawc/scrapers/HTMLSoupLinkScraper.py
nyawc/scrapers/JSONRegexLinkScraper.py
nyawc/scrapers/XMLRegexLinkScraper.py
nyawc/scrapers/__init__.py
test/__init__.py
test/test_helpers_url_helper.py
test/test_queue.py
test/test_scrapers_css_regex_link_scraper.py
test/test_scrapers_html_soup_form_scraper.py
test/test_scrapers_html_soup_link_scraper.py
test/test_scrapers_json_regex_link_scraper.py
test/test_scrapers_xml_regex_link_scraper.py
test/test_site.py