Metadata-Version: 1.1
Name: nyawc
Version: 1.8.1
Summary: A web crawler that gathers more than you can imagine.
Home-page: https://tijme.github.io/not-your-average-web-crawler/
Author: Tijme Gommers
Author-email: tijme@finnwea.com
License: MIT
Keywords: vulnerability,bug-bounty,security,post,get,request,crawler,scraper,scanner
Platform: any
Classifier: Development Status :: 5 - Production/Stable
Classifier: Environment :: Console
Classifier: Intended Audience :: Developers
Classifier: Intended Audience :: Education
Classifier: Intended Audience :: Information Technology
Classifier: Intended Audience :: System Administrators
Classifier: License :: OSI Approved :: MIT License
Classifier: Natural Language :: English
Classifier: Operating System :: MacOS
Classifier: Operating System :: Microsoft :: Windows
Classifier: Operating System :: POSIX :: Linux
Classifier: Programming Language :: Python :: 3.6
Classifier: Programming Language :: Python :: 3.5
Classifier: Programming Language :: Python :: 3.4
Classifier: Programming Language :: Python :: 3.3
Classifier: Programming Language :: Python :: 2.7
Classifier: Topic :: Security
